Dager/__init__.py
Dager/dager_data.py
Dager-0.7.dist-info/LICENSE
Dager-0.7.dist-info/METADATA
Dager-0.7.dist-info/WHEEL
Dager-0.7.dist-info/top_level.txt
Dager-0.7.dist-info/RECORD
